mysql_checksum/__init__.py
mysql_checksum/main.py
mysql_checksum-0.9.12.dist-info/licenses/LICENSE
mysql_checksum-0.9.12.dist-info/METADATA
mysql_checksum-0.9.12.dist-info/WHEEL
mysql_checksum-0.9.12.dist-info/entry_points.txt
mysql_checksum-0.9.12.dist-info/top_level.txt
mysql_checksum-0.9.12.dist-info/RECORD
