Metadata-Version: 2.4
Name: mysql_checksum
Version: 0.9.12
Author: demmonico
License-File: LICENSE
Dynamic: author
Dynamic: description
Dynamic: description-content-type
Dynamic: license-file
